backend/__init__.py
backend/app.py
backend/cli.py
backend/config.py
backend/index.html
backend/css/style.css
backend/js/api.js
backend/js/app.js
backend/js/canvas.js
backend/js/scrollbar.js
backend/trace/__init__.py
backend/trace/inst_rec.py
pipescope-0.6.0.dist-info/licenses/LICENSE
pipescope-0.6.0.dist-info/METADATA
pipescope-0.6.0.dist-info/WHEEL
pipescope-0.6.0.dist-info/entry_points.txt
pipescope-0.6.0.dist-info/top_level.txt
pipescope-0.6.0.dist-info/RECORD
